edf_helium_server/__init__.py
edf_helium_server/__version__.py
edf_helium_server/config.py
edf_helium_server/disk_usage.py
edf_helium_server/main.py
edf_helium_server/storage.py
edf_helium_server/synchronizer.py
edf_helium_server/analyzer/__init__.py
edf_helium_server/analyzer/helper.py
edf_helium_server/analyzer/task.py
edf_helium_server/api/__init__.py
edf_helium_server/api/case.py
edf_helium_server/api/config.py
edf_helium_server/api/disk_usage.py
edf_helium_server/helper/__init__.py
edf_helium_server/helper/aiohttp.py
edf_helium_server/helper/generaptor.py
edf_helium_server-2.0.0.dist-info/licenses/LICENSE
edf_helium_server-2.0.0.dist-info/METADATA
edf_helium_server-2.0.0.dist-info/WHEEL
edf_helium_server-2.0.0.dist-info/entry_points.txt
edf_helium_server-2.0.0.dist-info/top_level.txt
edf_helium_server-2.0.0.dist-info/RECORD
